pymongo_migrate/__init__.py
pymongo_migrate/cli.py
pymongo_migrate/generate.py
pymongo_migrate/graph_draw.py
pymongo_migrate/loader.py
pymongo_migrate/migrations.py
pymongo_migrate/mongo_migrate.py
pymongo_migrate-1.0.0.dist-info/LICENSE
pymongo_migrate-1.0.0.dist-info/METADATA
pymongo_migrate-1.0.0.dist-info/WHEEL
pymongo_migrate-1.0.0.dist-info/entry_points.txt
pymongo_migrate-1.0.0.dist-info/top_level.txt
pymongo_migrate-1.0.0.dist-info/RECORD
