Metadata-Version: 2.1
Name: pymongo-migrate
Version: 1.0.0
Summary: MongoDB data migration tool in Python
License: Apache Software License
Project-URL: Homepage, https://github.com/stxnext/pymongo-migrate
Project-URL: Changelog, https://github.com/stxnext/pymongo-migrate/blob/main/CHANGELOG.md
Keywords: mongo,mongodb,pymongo,migrate,migration
Classifier: License :: OSI Approved :: Apache Software License
Classifier: Operating System :: OS Independent
Classifier: Programming Language :: Python
Classifier: Programming Language :: Python :: 3
Classifier: Programming Language :: Python :: 3.8
Classifier: Programming Language :: Python :: 3.9
Classifier: Programming Language :: Python :: 3.10
Classifier: Programming Language :: Python :: 3.11
Classifier: Topic :: Software Development :: Libraries :: Python Modules
Classifier: Topic :: Database
Requires-Python: >=3.8
License-File: LICENSE
Requires-Dist: pymongo (>=3.7.2)
Requires-Dist: Click (>=7)
